SakiPy/__init__.py
SakiPy/_version.py
SakiPy/BankCard/__init__.py
SakiPy/BankCard/cardLook.py
SakiPy/Core/__init__.py
SakiPy/Core/core.py
SakiPy/Core/findDuplicates.py
SakiPy/Core/global_resource.py
SakiPy/Core/log.py
SakiPy/DatasDeal/__init__.py
SakiPy/DatasDeal/changeData.py
SakiPy/DatasDeal/datasDeal.py
SakiPy/DatasDeal/dealBankCCB.py
SakiPy/DatasDeal/dealDateAndTime.py
SakiPy/DatasDeal/pathDeal.py
SakiPy/DatasDeal/pdfDeal.py
SakiPy/DatasDeal/signDeal.py
SakiPy/DatasDeal/specialDeal.py
SakiPy/Resources/__init__.py
SakiPy/Resources/国家信息.xlsx
SakiPy/Resources/字典mapping表.xlsx
SakiPy/Resources/银行卡开户行识别模型.pkl
SakiPy/Resources/银行卡开户行识别模型【对应标签】.pkl
SakiPy/Resources/银行开户行字典.json
SakiPy/Resources/银行所属行.json
SakiPy/Resources/银行账户信息字典mapping表.xlsx
SakiPy-0.0.3.dist-info/METADATA
SakiPy-0.0.3.dist-info/WHEEL
SakiPy-0.0.3.dist-info/entry_points.txt
SakiPy-0.0.3.dist-info/top_level.txt
SakiPy-0.0.3.dist-info/RECORD
