Metadata-Version: 2.1
Name: SakiPy
Version: 0.0.3
Summary: SakiPy 是十六夜咲月自建的一个库
Home-page: https://github.com/Saki/SakiPy
Author: 十六夜咲月
Author-email: ma18387890737@outlook.com
Keywords: API,SakiPy,Python
Classifier: Programming Language :: Python :: 3
Classifier: License :: OSI Approved :: MIT License
Classifier: Operating System :: OS Independent
Requires-Python: >=3.10
Requires-Dist: numpy
Requires-Dist: joblib
Requires-Dist: pandas
Requires-Dist: scikit-learn
Requires-Dist: requests
Requires-Dist: chardet
Requires-Dist: typing-inspect
Requires-Dist: pdfplumber
Requires-Dist: PyPDF2
Requires-Dist: tqdm
Requires-Dist: colorama
